{
  "category": "EventDriven",
  "name": "EventDriven_20250523_173011",
  "description": "Message queue and event processing failures",
  "duration": 970,
  "metadata": {
    "generated_at": "2025-05-23T17:30:11.417054",
    "phrase_templates_used": 0,
    "total_events": 5,
    "severity_distribution": {
      "low": 0,
      "medium": 0,
      "high": 0
    }
  },
  "events": [
    {
      "timestamp": "2025-05-23T17:30:11.416956",
      "event_type": "trigger",
      "description": "Initial failure detected: rate limit exceeded",
      "injection_spec": null
    },
    {
      "timestamp": "2025-05-23T17:31:53.416956",
      "event_type": "queue_overflow",
      "description": "Queue_Overflow: database connection lost",
      "injection_spec": null
    },
    {
      "timestamp": "2025-05-23T17:32:05.416956",
      "event_type": "recovery",
      "description": "Recovery: queue overflow",
      "injection_spec": null
    },
    {
      "timestamp": "2025-05-23T17:32:54.416956",
      "event_type": "queue_overflow",
      "description": "Queue_Overflow: disk space full",
      "injection_spec": null
    },
    {
      "timestamp": "2025-05-23T17:46:21.416956",
      "event_type": "recovery",
      "description": "System recovered: message queue drained",
      "injection_spec": null
    }
  ]
}